qiskit_qasm3_import/__init__.py
qiskit_qasm3_import/api.py
qiskit_qasm3_import/converter.py
qiskit_qasm3_import/data.py
qiskit_qasm3_import/exceptions.py
qiskit_qasm3_import/expression.py
qiskit_qasm3_import/py.typed
qiskit_qasm3_import/state.py
qiskit_qasm3_import/types.py
qiskit_qasm3_import-0.5.0.dist-info/LICENSE
qiskit_qasm3_import-0.5.0.dist-info/METADATA
qiskit_qasm3_import-0.5.0.dist-info/WHEEL
qiskit_qasm3_import-0.5.0.dist-info/top_level.txt
qiskit_qasm3_import-0.5.0.dist-info/RECORD
