Metadata-Version: 2.1
Name: qiskit-qasm3-import
Version: 0.5.0
Summary: Importer for parsing OpenQASM 3 strings into Qiskit circuits
Home-page: https://github.com/Qiskit/qiskit-qasm3-import
Author: Jake Lishman
License: Apache 2.0 License
Project-URL: Bug Tracker, https://github.com/Qiskit/qiskit-qasm3-import/issues
Project-URL: Documentation, https://qiskit.github.io/qiskit-qasm3-import
Project-URL: Source Code, https://github.com/Qiskit/qiskit-qasm3-import
License-File: LICENSE
Requires-Dist: qiskit>=0.37.0
Requires-Dist: openqasm3[parser]<0.6,>=0.4
Provides-Extra: all
